{
    "Dialog": {
        "Leaderboard": "Edetabel",
        "Confirm group password": "Kinnitage rühma parool",
        "Password": "Parool",
        "Ban user": "Blokeeri kasutaja",
        "Leaderboard Config (Fixed by Shige)": "Edetabeli konfiguratsioon (parandatud Shige'i poolt)",
        "Sign-up": "Registreeri",
        "Log-in": "Logi sisse",
        "Delete account": "Kustuta konto",
        "Log-out": "Logi välja",
        "Change username": "Muuda kasutajanime",
        "Email address": "E-posti aadress",
        "Username": "Kasutajanimi",
        "New username": "Uus kasutajanimi",
        "Repeat password": "Korda salasõna",
        "Sign up": "Registreeri",
        "Reset password": "Lähtestage parool",
        "You are not logged in.": "Sa pole sisse loginud.",
        "Bio:": "Oli:",
        "A message that everyone can see when clicking on your username (max. 280 characters). You can use markdown to embed links.": "Sõnum, mida kõik näevad sinu kasutajanimele klõpsates (max 280 tähemärki). Linkide manustamiseks saate kasutada allahindlust.",
        "Set Bio": "Määra bio",
        "Account": "Konto",
        "Home screen": "Avakuva",
        "Show the home screen leaderboard (only works with Anki 2.1.20+)": "Kuva avaekraani edetabel (töötab ainult versiooniga Anki 2.1.20+)",
        "Focus on user": "Keskendu kasutajale",
        "Maximum number of users on the home screen Leaderboard:": "Maksimaalne kasutajate arv avakuva edetabelis:",
        "General": "Kindral",
        "Sync when deck is finished (only works with Anki 2.1.20+)": "Sünkroonimine, kui teki on valmis (töötab ainult versiooniga Anki 2.1.20+)",
        "Global": "Globaalne",
        "Friends": "Sõbrad",
        "Country": "Riik",
        "Group": "Grupp",
        "League": "Liiga",
        "Sort by:": "Sorteerima:",
        "Reviews": "Arvustused",
        "Time": "Aeg",
        "Streak": "Riba",
        "Reviews past 31 days": "Arvustused viimase 31 päeva jooksul",
        "Retention": "Säilitamine",
        "hours past midnight": "tundi üle kesköö",
        "The next day starts": "Järgmine päev algab",
        "Default Leaderboard:": "Vaikimisi edetabel:",
        "Automatically scroll to user": "Kerige automaatselt kasutajani",
        "Show league medals next to username": "Kuva liigamedalid kasutajanime kõrval",
        "Settings": "Seaded",
        "Create new group": "Loo uus grupp",
        "Create group": "Loo grupp",
        "Repeat password:": "Korda salasõna:",
        "optional": "valikuline",
        "Group name": "Grupi nimi",
        "Password:": "Parool:",
        "Join/Leave group": "Liitu/lahku grupiga",
        "Join a group": "Liituge grupiga",
        "If it's a private group, please enter the password:": "Kui see on privaatne grupp, sisestage parool:",
        "Join group": "Liitu grupiga",
        "Leave group": "Lahku rühmast",
        "Manage groups": "Hallake rühmi",
        "Old password:": "Vana parool:",
        "Select a group you're an admin of": "Valige grupp, mille administraator olete",
        "Add admin:": "Lisa administraator:",
        "Save": "Salvesta",
        "leave empty if it's currently not password protected": "jätke tühjaks, kui see pole praegu parooliga kaitstud",
        "New password": "Uus salasõna",
        "Groups": "Grupid",
        "Friend": "sõber",
        "Remove": "Eemalda",
        "Import": "Import",
        "Export": "Ekspordi",
        "Add": "Lisama",
        "Your friends:": "Sinu sõbrad:",
        "Add friend:": "Lisa sõber:",
        "Unhide": "paljastada",
        "Hidden Users": "Varjatud kasutajad",
        "About": "Umbes",
        "Report user": "Teata kasutajast",
        "Please explain why you want to report [user]:": "Selgitage, miks soovite [kasutajast] teatada:",
        "Send email to reset password": "Parooli lähtestamiseks saatke meil",
        "User": "Kasutaja",
        "Hide user": "Peida kasutaja",
        "Report": "Aruanne",
        "Medals: None": "Medalid: pole",
        "History:": "Ajalugu:",
        "Bio": "Ta oli",
        "Ban from group": "Grupist keeldumine",
        "League: None": "Liiga: Pole",
        "Country: None": "Riik: puudub",
        "Add friend": "Lisa sõber",
        "Groups:": "Grupid:",
        "Season": "Hooaeg",
        "Rank": "Koht",
        "XP": "XP"
    },
    "dialog": {
        "Leaderboard (Fixed by Shige)": "Edetabel (parandatud Shige'i poolt)",
        "Username": "Kasutajanimi",
        "Reviews today": "Tänased ülevaated",
        "Minutes today": "Täna minutid",
        "Streak": "Riba",
        "Past 31 days": "Viimased 31 päeva",
        "Retention %": "Säilitamise %",
        "Global": "Globaalne",
        "Friends": "Sõbrad",
        "Country": "Riik",
        "Groups": "Grupid",
        "League Name": "Liiga nimi",
        "00 days 00 hours remaining": "00 päeva 00 tundi jäänud",
        "XP": "XP",
        "Minutes": "Minutid",
        "Reviews": "Arvustused",
        "Days studied %": "Uuritud päevade %",
        "League": "Liiga"
    },
    "Leaderboard_menu": {
        "&Open leaderboard": "&Ava edetabel",
        "&Sync and update": "&Sünkroonimine ja värskendamine",
        "&Config": "&Konfig",
        "&Help": "&Abi"
    },
    "how_to_use_tr": {
        "How to use": "Kuidas kasutada",
        "This add-on ranks all of its users by the number of cards reviewed today, time spend studying today, current streak, reviews in the past 31 days, and retention.": "See lisandmoodul reastab kõik kasutajad täna üle vaadatud kaartide arvu, täna õppimisele kulutatud aja, praeguse jada, viimase 31 päeva arvustuste ja säilitamise järgi.",
        "You can also compete against friends, join groups, and join a country leaderboard.": "Samuti saate võistelda sõpradega, liituda gruppidega ja liituda riigi edetabeliga.",
        "You'll only see users, that synced on the same day as you.": "Näete ainult kasutajaid, kes on sünkroonitud teiega samal päeval.",
        "League": "Liiga",
        "In the league tab, you see everyone who synced at least once during the current season. There are four leagues (Alpha, Beta, Gamma, and Delta).": "Liiga vahekaardil näete kõiki, kes on jooksva hooaja jooksul vähemalt korra sünkrooninud. Liigasid on neli (alfa, beeta, gamma ja delta).",
        "Season": "Hooaeg",
        "A season lasts two weeks. You don't have to sync every day.": "Hooaeg kestab kaks nädalat. Te ei pea iga päev sünkroonima.",
        "Group": "Grupp",
        "By default, there are public groups for Medicine, Language, and Pokemon.(pass 1234)": "Vaikimisi on meditsiini, keele ja pokemonite jaoks avalikud rühmad. (pass 1234)",
        "If you want to delete the group, please contact me.": "Kui soovite grupi kustutada, võtke minuga ühendust.",
        "XP formula": "XP valem",
        "XP = days studied percentage x ((6 x time) + (2 x reviews x retention))": "XP = uuritud päevade protsent x ((6 x aeg) + (2 x arvustused x säilitamine))",
        "You have to study at least 5 minutes per day. Otherwise, this day won't be counted as “studied” (See this issue for more info).": "Peate õppima vähemalt 5 minutit päevas. Vastasel juhul ei loeta seda päeva „õpituks” (lisateabe saamiseks vaadake seda numbrit).",
        "At the end of each season, the top 20% will be promoted, and the last 20% will be relegated.": "Iga hooaja lõpus tõstetakse 20% parimat ja viimased 20% langevad välja.",
        "Website": "Veebileht",
        "You can check the leaderboard (past 24 hours) on this website.": "Edetabelit (viimase 24 tunni jooksul) saate vaadata sellelt veebisaidilt.",
        "Related Add-ons (Created by Shige)": "Seotud lisandmoodulid (looja Shige)"
    }
}